farmfs/__init__.py
farmfs/blobstore.py
farmfs/fs.py
farmfs/keydb.py
farmfs/remote.py
farmfs/snapshot.py
farmfs/transduce.py
farmfs/ui.py
farmfs/util.py
farmfs/volume.py
farmfs-0.8.2.data/scripts/snap.sh
farmfs-0.8.2.dist-info/LICENSE
farmfs-0.8.2.dist-info/METADATA
farmfs-0.8.2.dist-info/WHEEL
farmfs-0.8.2.dist-info/entry_points.txt
farmfs-0.8.2.dist-info/top_level.txt
farmfs-0.8.2.dist-info/RECORD
