Metadata-Version: 2.1
Name: farmfs
Version: 0.8.2
Summary: tool which de-duplicates files in a filesystem by checksum.
Home-page: http://github.com/andrewguy9/farmfs
Author: Andrew Thomson
Author-email: athomsonguy@gmail.com
License: MIT
Platform: UNKNOWN
Classifier: Development Status :: 4 - Beta
Classifier: License :: OSI Approved :: MIT License
Classifier: Topic :: System :: Filesystems
Classifier: Programming Language :: Python :: 3.7
Classifier: Programming Language :: Python :: 2.7
Requires-Dist: func-prototypes (>=0.5.0)
Requires-Dist: docopt
Requires-Dist: delnone
Requires-Dist: future
Requires-Dist: safeoutput (>=2.0)
Requires-Dist: filetype (==1.0.6)
Requires-Dist: S3Lib (>=1.3.0)
